.gitignore
MANIFEST.in
README.rst
bootstrap.py
buildout.cfg
setup.py
collective/__init__.py
collective.js.easing.egg-info/PKG-INFO
collective.js.easing.egg-info/SOURCES.txt
collective.js.easing.egg-info/dependency_links.txt
collective.js.easing.egg-info/entry_points.txt
collective.js.easing.egg-info/namespace_packages.txt
collective.js.easing.egg-info/not-zip-safe
collective.js.easing.egg-info/requires.txt
collective.js.easing.egg-info/top_level.txt
collective/js/__init__.py
collective/js/easing/__init__.py
collective/js/easing/configure.zcml
collective/js/easing/vocabulary.py
collective/js/easing/profiles/default/jsregistry.xml
collective/js/easing/profiles/default/metadata.xml
collective/js/easing/resources/jquery.easing.js
docs/HISTORY.txt