Metadata-Version: 1.0
Name: collective.js.easing
Version: 1.0
Summary: JQuery easing plugin registration for the Plone CMS
Home-page: https://github.com/collective/collective.js.easing
Author: JeanMichel FRANCOIS aka toutpt
Author-email: toutpt@gmail.com
License: GPL
Platform: UNKNOWN
Classifier: Framework :: Plone
Classifier: Framework :: Plone :: 4.0
Classifier: Framework :: Plone :: 4.1
Classifier: Programming Language :: Python
